infi.win32service-0.1.9-py2.7-nspkg.pth
infi/win32service/__init__.py
infi/win32service/__version__.py
infi/win32service/common.py
infi/win32service/service.py
infi/win32service/service_control_manager.py
infi/win32service/service_runner.py
infi/win32service/utils.py
infi.win32service-0.1.9.dist-info/DESCRIPTION.rst
infi.win32service-0.1.9.dist-info/METADATA
infi.win32service-0.1.9.dist-info/RECORD
infi.win32service-0.1.9.dist-info/WHEEL
infi.win32service-0.1.9.dist-info/entry_points.txt
infi.win32service-0.1.9.dist-info/metadata.json
infi.win32service-0.1.9.dist-info/namespace_packages.txt
infi.win32service-0.1.9.dist-info/top_level.txt
