Metadata-Version: 2.0
Name: infi.win32service
Version: 0.1.9
Summary: Python bindings to Windows ServiceControlManager
Home-page: https://github.com/Infinidat/infi.win32service
Author: Arnon Yaari
Author-email: arnony@infinidat.com
License: BSD
Platform: UNKNOWN
Classifier: Intended Audience :: Developers
Classifier: Intended Audience :: System Administrators
Classifier: License :: OSI Approved :: BSD License
Classifier: Operating System :: OS Independent
Classifier: Programming Language :: Python
Classifier: Programming Language :: Python :: 2
Classifier: Programming Language :: Python :: 3
Classifier: Topic :: Software Development :: Libraries :: Python Modules
Requires-Dist: setuptools
Requires-Dist: six
